xdeap/__init__.py
xdeap/fitness_with_constraints.py
xdeap/nsga2_tools.py
xdeap-1.0.0.dist-info/METADATA
xdeap-1.0.0.dist-info/RECORD
xdeap-1.0.0.dist-info/WHEEL
xdeap-1.0.0.dist-info/top_level.txt
