Metadata-Version: 2.1
Name: xdeap
Version: 1.0.0
Summary: Extensions to DEAP
Home-page: https://github.com/ChristopherMayes/xdeap
Author: Christopher Mayes
License: UNKNOWN
Keywords: optimization constraints deap
Platform: UNKNOWN
Classifier: Development Status :: 3 - Alpha
Classifier: Intended Audience :: Developers
Classifier: Topic :: Software Development :: Build Tools
Classifier: License :: OSI Approved :: MIT License
Classifier: Programming Language :: Python :: 3
Classifier: Programming Language :: Python :: 3.4
Classifier: Programming Language :: Python :: 3.5
Classifier: Programming Language :: Python :: 3.6
Classifier: Programming Language :: Python :: 3.7
Requires-Dist: deap
